icebreaker/KNN_segmenter.py
icebreaker/__init__.py
icebreaker/average_mask.py
icebreaker/correct_path.py
icebreaker/filter_designer.py
icebreaker/filter_designer_not_normalized.py
icebreaker/five_figures.py
icebreaker/ib_group_template.star
icebreaker/ib_job_template_FLATTEN_MODE.star
icebreaker/ib_job_template_GROUP_MODE.star
icebreaker/ice_groups.py
icebreaker/icebreaker_equalize_multi.py
icebreaker/icebreaker_icegroups_multi.py
icebreaker/listdir.py
icebreaker/local_mask.py
icebreaker/original_mask.py
icebreaker/original_mask_fast.py
icebreaker/plot_boxplots.py
icebreaker/show_gradient.py
icebreaker/star_appender.py
icebreaker/window_mean.py
icebreaker/cli/__init__.py
icebreaker/cli/ib_5fig.py
icebreaker/cli/ib_group.py
icebreaker/cli/ib_job.py
icebreaker/cli/micrographs_enhance.py
icebreaker/cli/micrographs_group.py
icebreaker/cli/particles_group.py
icebreaker/cli/stats.py
icebreaker_em-0.3.9.dist-info/LICENSE
icebreaker_em-0.3.9.dist-info/METADATA
icebreaker_em-0.3.9.dist-info/WHEEL
icebreaker_em-0.3.9.dist-info/entry_points.txt
icebreaker_em-0.3.9.dist-info/top_level.txt
icebreaker_em-0.3.9.dist-info/RECORD
