Metadata-Version: 2.1
Name: icebreaker-em
Version: 0.3.9
Summary: UNKNOWN
Home-page: UNKNOWN
License: BSD
Project-URL: Download, https://github.com/DiamondLightSource/python-icebreaker/releases
Project-URL: Documentation, https://github.com/DiamondLightSource/python-icebreaker
Project-URL: GitHub, https://github.com/DiamondLightSource/python-icebreaker
Project-URL: Bug-Tracker, https://github.com/DiamondLightSource/python-icebreaker/issues
Platform: UNKNOWN
Classifier: License :: OSI Approved :: BSD License
Classifier: Programming Language :: Python :: 3
Classifier: Programming Language :: Python :: 3.6
Classifier: Programming Language :: Python :: 3.7
Classifier: Programming Language :: Python :: 3.8
Classifier: Programming Language :: Python :: 3.9
Requires-Python: >=3.6
License-File: LICENSE
Requires-Dist: gemmi
Requires-Dist: matplotlib
Requires-Dist: mrcfile
Requires-Dist: numpy
Requires-Dist: opencv-python-headless
Requires-Dist: scipy
